dkredis/__init__.py
dkredis/dkredis.py
dkredis/dkredislocks.py
dkredis/rediscache.py
dkredis/utils.py
dkredis-1.0.2.dist-info/LICENSE
dkredis-1.0.2.dist-info/METADATA
dkredis-1.0.2.dist-info/WHEEL
dkredis-1.0.2.dist-info/top_level.txt
dkredis-1.0.2.dist-info/RECORD
