Metadata-Version: 2.1
Name: dkredis
Version: 1.0.2
Summary: dkredis - Python interface to Redis
Home-page: https://github.com/datakortet/dkredis
Author: bjorn
Author-email: bp@datakortet.no
License: MIT
Keywords: redis
Classifier: Development Status :: 5 - Production/Stable
Classifier: Intended Audience :: Developers
Classifier: Programming Language :: Python
Classifier: Programming Language :: Python :: 3
Classifier: Topic :: Software Development :: Libraries
License-File: LICENSE
Requires-Dist: redis ==5.0.1
